mkdocs_replace_markdown/__init__.py
mkdocs_replace_markdown/plugin.py
mkdocs_replace_markdown-0.1.0.dist-info/LICENSE
mkdocs_replace_markdown-0.1.0.dist-info/METADATA
mkdocs_replace_markdown-0.1.0.dist-info/WHEEL
mkdocs_replace_markdown-0.1.0.dist-info/entry_points.txt
mkdocs_replace_markdown-0.1.0.dist-info/top_level.txt
mkdocs_replace_markdown-0.1.0.dist-info/RECORD
